{"nodes": [{"id": "home_martin_dominion_dominion_ai_planner_py", "label": "planner.py", "file_type": "code", "source_file": "/home/Martin/Dominion/dominion_ai/planner.py", "source_location": "L1"}, {"id": "dominion_ai_planner_filters", "label": "_filters()", "file_type": "code", "source_file": "/home/Martin/Dominion/dominion_ai/planner.py", "source_location": "L21"}, {"id": "str", "label": "str", "file_type": "code", "source_file": "/home/Martin/Dominion/dominion_ai/planner.py", "source_location": "L21"}, {"id": "any", "label": "Any", "file_type": "code", "source_file": "/home/Martin/Dominion/dominion_ai/planner.py", "source_location": "L21"}, {"id": "dominion_ai_planner_plan", "label": "plan()", "file_type": "code", "source_file": "/home/Martin/Dominion/dominion_ai/planner.py", "source_location": "L35"}, {"id": "retrievalplan", "label": "RetrievalPlan", "file_type": "code", "source_file": "/home/Martin/Dominion/dominion_ai/planner.py", "source_location": "L35"}], "edges": [{"source": "home_martin_dominion_dominion_ai_planner_py", "target": "re", "relation": "imports", "context": "import", "confidence": "EXTRACTED", "source_file": "/home/Martin/Dominion/dominion_ai/planner.py", "source_location": "L3", "weight": 1.0}, {"source": "home_martin_dominion_dominion_ai_planner_py", "target": "typing", "relation": "imports_from", "context": "import", "confidence": "EXTRACTED", "source_file": "/home/Martin/Dominion/dominion_ai/planner.py", "source_location": "L4", "weight": 1.0}, {"source": "home_martin_dominion_dominion_ai_planner_py", "target": "home_martin_dominion_dominion_ai_obs_py", "relation": "imports_from", "context": "import", "confidence": "EXTRACTED", "source_file": "/home/Martin/Dominion/dominion_ai/planner.py", "source_location": "L6", "weight": 1.0}, {"source": "home_martin_dominion_dominion_ai_planner_py", "target": "home_martin_dominion_dominion_ai_types_py", "relation": "imports_from", "context": "import", "confidence": "EXTRACTED", "source_file": "/home/Martin/Dominion/dominion_ai/planner.py", "source_location": "L7", "weight": 1.0}, {"source": "home_martin_dominion_dominion_ai_planner_py", "target": "dominion_ai_planner_filters", "relation": "contains", "confidence": "EXTRACTED", "source_file": "/home/Martin/Dominion/dominion_ai/planner.py", "source_location": "L21", "weight": 1.0}, {"source": "dominion_ai_planner_filters", "target": "str", "relation": "references", "context": "parameter_type", "confidence": "EXTRACTED", "source_file": "/home/Martin/Dominion/dominion_ai/planner.py", "source_location": "L21", "weight": 1.0}, {"source": "dominion_ai_planner_filters", "target": "str", "relation": "references", "context": "generic_arg", "confidence": "EXTRACTED", "source_file": "/home/Martin/Dominion/dominion_ai/planner.py", "source_location": "L21", "weight": 1.0}, {"source": "dominion_ai_planner_filters", "target": "any", "relation": "references", "context": "generic_arg", "confidence": "EXTRACTED", "source_file": "/home/Martin/Dominion/dominion_ai/planner.py", "source_location": "L21", "weight": 1.0}, {"source": "home_martin_dominion_dominion_ai_planner_py", "target": "dominion_ai_planner_plan", "relation": "contains", "confidence": "EXTRACTED", "source_file": "/home/Martin/Dominion/dominion_ai/planner.py", "source_location": "L35", "weight": 1.0}, {"source": "dominion_ai_planner_plan", "target": "str", "relation": "references", "context": "parameter_type", "confidence": "EXTRACTED", "source_file": "/home/Martin/Dominion/dominion_ai/planner.py", "source_location": "L35", "weight": 1.0}, {"source": "dominion_ai_planner_plan", "target": "str", "relation": "references", "context": "generic_arg", "confidence": "EXTRACTED", "source_file": "/home/Martin/Dominion/dominion_ai/planner.py", "source_location": "L35", "weight": 1.0}, {"source": "dominion_ai_planner_plan", "target": "any", "relation": "references", "context": "generic_arg", "confidence": "EXTRACTED", "source_file": "/home/Martin/Dominion/dominion_ai/planner.py", "source_location": "L35", "weight": 1.0}, {"source": "dominion_ai_planner_plan", "target": "retrievalplan", "relation": "references", "context": "return_type", "confidence": "EXTRACTED", "source_file": "/home/Martin/Dominion/dominion_ai/planner.py", "source_location": "L35", "weight": 1.0}, {"source": "dominion_ai_planner_plan", "target": "str", "relation": "calls", "context": "call", "confidence": "EXTRACTED", "source_file": "/home/Martin/Dominion/dominion_ai/planner.py", "source_location": "L37", "weight": 1.0}, {"source": "dominion_ai_planner_plan", "target": "retrievalplan", "relation": "calls", "context": "call", "confidence": "EXTRACTED", "source_file": "/home/Martin/Dominion/dominion_ai/planner.py", "source_location": "L54", "weight": 1.0}, {"source": "dominion_ai_planner_plan", "target": "dominion_ai_planner_filters", "relation": "calls", "context": "call", "confidence": "EXTRACTED", "source_file": "/home/Martin/Dominion/dominion_ai/planner.py", "source_location": "L58", "weight": 1.0}], "raw_calls": [{"caller_nid": "dominion_ai_planner_filters", "callee": "lower", "is_member_call": true, "source_file": "/home/Martin/Dominion/dominion_ai/planner.py", "source_location": "L22"}, {"caller_nid": "dominion_ai_planner_plan", "callee": "get", "is_member_call": true, "source_file": "/home/Martin/Dominion/dominion_ai/planner.py", "source_location": "L37"}, {"caller_nid": "dominion_ai_planner_plan", "callee": "new_trace_id", "is_member_call": false, "source_file": "/home/Martin/Dominion/dominion_ai/planner.py", "source_location": "L37"}, {"caller_nid": "dominion_ai_planner_plan", "callee": "span", "is_member_call": false, "source_file": "/home/Martin/Dominion/dominion_ai/planner.py", "source_location": "L38"}, {"caller_nid": "dominion_ai_planner_plan", "callee": "lower", "is_member_call": true, "source_file": "/home/Martin/Dominion/dominion_ai/planner.py", "source_location": "L39"}, {"caller_nid": "dominion_ai_planner_plan", "callee": "search", "is_member_call": true, "source_file": "/home/Martin/Dominion/dominion_ai/planner.py", "source_location": "L44"}, {"caller_nid": "dominion_ai_planner_plan", "callee": "extend", "is_member_call": true, "source_file": "/home/Martin/Dominion/dominion_ai/planner.py", "source_location": "L47"}, {"caller_nid": "dominion_ai_planner_plan", "callee": "get", "is_member_call": true, "source_file": "/home/Martin/Dominion/dominion_ai/planner.py", "source_location": "L49"}, {"caller_nid": "dominion_ai_planner_plan", "callee": "max", "is_member_call": false, "source_file": "/home/Martin/Dominion/dominion_ai/planner.py", "source_location": "L51"}, {"caller_nid": "dominion_ai_planner_plan", "callee": "int", "is_member_call": false, "source_file": "/home/Martin/Dominion/dominion_ai/planner.py", "source_location": "L52"}, {"caller_nid": "dominion_ai_planner_plan", "callee": "get", "is_member_call": true, "source_file": "/home/Martin/Dominion/dominion_ai/planner.py", "source_location": "L52"}, {"caller_nid": "dominion_ai_planner_plan", "callee": "get", "is_member_call": true, "source_file": "/home/Martin/Dominion/dominion_ai/planner.py", "source_location": "L53"}, {"caller_nid": "dominion_ai_planner_plan", "callee": "list", "is_member_call": false, "source_file": "/home/Martin/Dominion/dominion_ai/planner.py", "source_location": "L57"}, {"caller_nid": "dominion_ai_planner_plan", "callee": "fromkeys", "is_member_call": true, "source_file": "/home/Martin/Dominion/dominion_ai/planner.py", "source_location": "L57"}, {"caller_nid": "dominion_ai_planner_plan", "callee": "dict", "is_member_call": false, "source_file": "/home/Martin/Dominion/dominion_ai/planner.py", "source_location": "L58"}, {"caller_nid": "dominion_ai_planner_plan", "callee": "get", "is_member_call": true, "source_file": "/home/Martin/Dominion/dominion_ai/planner.py", "source_location": "L58"}, {"caller_nid": "dominion_ai_planner_plan", "callee": "max", "is_member_call": false, "source_file": "/home/Martin/Dominion/dominion_ai/planner.py", "source_location": "L59"}, {"caller_nid": "dominion_ai_planner_plan", "callee": "int", "is_member_call": false, "source_file": "/home/Martin/Dominion/dominion_ai/planner.py", "source_location": "L59"}, {"caller_nid": "dominion_ai_planner_plan", "callee": "get", "is_member_call": true, "source_file": "/home/Martin/Dominion/dominion_ai/planner.py", "source_location": "L59"}, {"caller_nid": "dominion_ai_planner_plan", "callee": "max", "is_member_call": false, "source_file": "/home/Martin/Dominion/dominion_ai/planner.py", "source_location": "L60"}, {"caller_nid": "dominion_ai_planner_plan", "callee": "int", "is_member_call": false, "source_file": "/home/Martin/Dominion/dominion_ai/planner.py", "source_location": "L60"}, {"caller_nid": "dominion_ai_planner_plan", "callee": "get", "is_member_call": true, "source_file": "/home/Martin/Dominion/dominion_ai/planner.py", "source_location": "L60"}, {"caller_nid": "dominion_ai_planner_plan", "callee": "get", "is_member_call": true, "source_file": "/home/Martin/Dominion/dominion_ai/planner.py", "source_location": "L61"}, {"caller_nid": "dominion_ai_planner_plan", "callee": "get", "is_member_call": true, "source_file": "/home/Martin/Dominion/dominion_ai/planner.py", "source_location": "L62"}]}