{"nodes": [{"id": "home_martin_dominion_data_pipeline_sources_base_py", "label": "base.py", "file_type": "code", "source_file": "/home/Martin/Dominion/data_pipeline/sources/base.py", "source_location": "L1"}, {"id": "sources_base_datasource", "label": "DataSource", "file_type": "code", "source_file": "/home/Martin/Dominion/data_pipeline/sources/base.py", "source_location": "L8"}, {"id": "abc", "label": "ABC", "file_type": "code", "source_file": "", "source_location": ""}, {"id": "sources_base_datasource_init", "label": ".__init__()", "file_type": "code", "source_file": "/home/Martin/Dominion/data_pipeline/sources/base.py", "source_location": "L11"}, {"id": "str", "label": "str", "file_type": "code", "source_file": "/home/Martin/Dominion/data_pipeline/sources/base.py", "source_location": "L11"}, {"id": "sources_base_fetch", "label": "fetch()", "file_type": "code", "source_file": "/home/Martin/Dominion/data_pipeline/sources/base.py", "source_location": "L19"}, {"id": "datetime", "label": "datetime", "file_type": "code", "source_file": "/home/Martin/Dominion/data_pipeline/sources/base.py", "source_location": "L19"}, {"id": "dataframe", "label": "DataFrame", "file_type": "code", "source_file": "/home/Martin/Dominion/data_pipeline/sources/base.py", "source_location": "L19"}, {"id": "sources_base_validate", "label": "validate()", "file_type": "code", "source_file": "/home/Martin/Dominion/data_pipeline/sources/base.py", "source_location": "L28"}, {"id": "bool", "label": "bool", "file_type": "code", "source_file": "/home/Martin/Dominion/data_pipeline/sources/base.py", "source_location": "L28"}, {"id": "sources_base_datasource_health", "label": ".health()", "file_type": "code", "source_file": "/home/Martin/Dominion/data_pipeline/sources/base.py", "source_location": "L32"}, {"id": "sources_base_datasource_mark_success", "label": ".mark_success()", "file_type": "code", "source_file": "/home/Martin/Dominion/data_pipeline/sources/base.py", "source_location": "L41"}, {"id": "sources_base_datasource_mark_error", "label": ".mark_error()", "file_type": "code", "source_file": "/home/Martin/Dominion/data_pipeline/sources/base.py", "source_location": "L47"}, {"id": "sources_base_rationale_1", "label": "Abstract base class for data sources.", "file_type": "rationale", "source_file": "/home/Martin/Dominion/data_pipeline/sources/base.py", "source_location": "L1"}, {"id": "sources_base_rationale_9", "label": "Base class for all data sources.", "file_type": "rationale", "source_file": "/home/Martin/Dominion/data_pipeline/sources/base.py", "source_location": "L9"}, {"id": "sources_base_rationale_20", "label": "Fetch data from source.          Returns:             DataFrame with columns: ti", "file_type": "rationale", "source_file": "/home/Martin/Dominion/data_pipeline/sources/base.py", "source_location": "L20"}, {"id": "sources_base_rationale_29", "label": "Validate fetched data meets quality requirements.", "file_type": "rationale", "source_file": "/home/Martin/Dominion/data_pipeline/sources/base.py", "source_location": "L29"}, {"id": "sources_base_rationale_33", "label": "Return health status of this source.", "file_type": "rationale", "source_file": "/home/Martin/Dominion/data_pipeline/sources/base.py", "source_location": "L33"}, {"id": "sources_base_rationale_42", "label": "Record successful fetch.", "file_type": "rationale", "source_file": "/home/Martin/Dominion/data_pipeline/sources/base.py", "source_location": "L42"}], "edges": [{"source": "home_martin_dominion_data_pipeline_sources_base_py", "target": "abc", "relation": "imports_from", "context": "import", "confidence": "EXTRACTED", "source_file": "/home/Martin/Dominion/data_pipeline/sources/base.py", "source_location": "L2", "weight": 1.0}, {"source": "home_martin_dominion_data_pipeline_sources_base_py", "target": "typing", "relation": "imports_from", "context": "import", "confidence": "EXTRACTED", "source_file": "/home/Martin/Dominion/data_pipeline/sources/base.py", "source_location": "L3", "weight": 1.0}, {"source": "home_martin_dominion_data_pipeline_sources_base_py", "target": "pandas", "relation": "imports", "context": "import", "confidence": "EXTRACTED", "source_file": "/home/Martin/Dominion/data_pipeline/sources/base.py", "source_location": "L4", "weight": 1.0}, {"source": "home_martin_dominion_data_pipeline_sources_base_py", "target": "datetime", "relation": "imports_from", "context": "import", "confidence": "EXTRACTED", "source_file": "/home/Martin/Dominion/data_pipeline/sources/base.py", "source_location": "L5", "weight": 1.0}, {"source": "home_martin_dominion_data_pipeline_sources_base_py", "target": "sources_base_datasource", "relation": "contains", "confidence": "EXTRACTED", "source_file": "/home/Martin/Dominion/data_pipeline/sources/base.py", "source_location": "L8", "weight": 1.0}, {"source": "sources_base_datasource", "target": "abc", "relation": "inherits", "confidence": "EXTRACTED", "source_file": "/home/Martin/Dominion/data_pipeline/sources/base.py", "source_location": "L8", "weight": 1.0}, {"source": "sources_base_datasource", "target": "sources_base_datasource_init", "relation": "method", "confidence": "EXTRACTED", "source_file": "/home/Martin/Dominion/data_pipeline/sources/base.py", "source_location": "L11", "weight": 1.0}, {"source": "sources_base_datasource_init", "target": "str", "relation": "references", "context": "parameter_type", "confidence": "EXTRACTED", "source_file": "/home/Martin/Dominion/data_pipeline/sources/base.py", "source_location": "L11", "weight": 1.0}, {"source": "home_martin_dominion_data_pipeline_sources_base_py", "target": "sources_base_fetch", "relation": "contains", "confidence": "EXTRACTED", "source_file": "/home/Martin/Dominion/data_pipeline/sources/base.py", "source_location": "L19", "weight": 1.0}, {"source": "sources_base_fetch", "target": "datetime", "relation": "references", "context": "generic_arg", "confidence": "EXTRACTED", "source_file": "/home/Martin/Dominion/data_pipeline/sources/base.py", "source_location": "L19", "weight": 1.0}, {"source": "sources_base_fetch", "target": "datetime", "relation": "references", "context": "generic_arg", "confidence": "EXTRACTED", "source_file": "/home/Martin/Dominion/data_pipeline/sources/base.py", "source_location": "L19", "weight": 1.0}, {"source": "sources_base_fetch", "target": "dataframe", "relation": "references", "context": "return_type", "confidence": "EXTRACTED", "source_file": "/home/Martin/Dominion/data_pipeline/sources/base.py", "source_location": "L19", "weight": 1.0}, {"source": "home_martin_dominion_data_pipeline_sources_base_py", "target": "sources_base_validate", "relation": "contains", "confidence": "EXTRACTED", "source_file": "/home/Martin/Dominion/data_pipeline/sources/base.py", "source_location": "L28", "weight": 1.0}, {"source": "sources_base_validate", "target": "dataframe", "relation": "references", "context": "parameter_type", "confidence": "EXTRACTED", "source_file": "/home/Martin/Dominion/data_pipeline/sources/base.py", "source_location": "L28", "weight": 1.0}, {"source": "sources_base_validate", "target": "bool", "relation": "references", "context": "return_type", "confidence": "EXTRACTED", "source_file": "/home/Martin/Dominion/data_pipeline/sources/base.py", "source_location": "L28", "weight": 1.0}, {"source": "sources_base_datasource", "target": "sources_base_datasource_health", "relation": "method", "confidence": "EXTRACTED", "source_file": "/home/Martin/Dominion/data_pipeline/sources/base.py", "source_location": "L32", "weight": 1.0}, {"source": "sources_base_datasource", "target": "sources_base_datasource_mark_success", "relation": "method", "confidence": "EXTRACTED", "source_file": "/home/Martin/Dominion/data_pipeline/sources/base.py", "source_location": "L41", "weight": 1.0}, {"source": "sources_base_datasource", "target": "sources_base_datasource_mark_error", "relation": "method", "confidence": "EXTRACTED", "source_file": "/home/Martin/Dominion/data_pipeline/sources/base.py", "source_location": "L47", "weight": 1.0}, {"source": "sources_base_datasource_mark_error", "target": "str", "relation": "references", "context": "parameter_type", "confidence": "EXTRACTED", "source_file": "/home/Martin/Dominion/data_pipeline/sources/base.py", "source_location": "L47", "weight": 1.0}, {"source": "sources_base_rationale_1", "target": "home_martin_dominion_data_pipeline_sources_base_py", "relation": "rationale_for", "confidence": "EXTRACTED", "source_file": "/home/Martin/Dominion/data_pipeline/sources/base.py", "source_location": "L1", "weight": 1.0}, {"source": "sources_base_rationale_9", "target": "sources_base_datasource", "relation": "rationale_for", "confidence": "EXTRACTED", "source_file": "/home/Martin/Dominion/data_pipeline/sources/base.py", "source_location": "L9", "weight": 1.0}, {"source": "sources_base_rationale_20", "target": "sources_base_datasource_fetch", "relation": "rationale_for", "confidence": "EXTRACTED", "source_file": "/home/Martin/Dominion/data_pipeline/sources/base.py", "source_location": "L20", "weight": 1.0}, {"source": "sources_base_rationale_29", "target": "sources_base_datasource_validate", "relation": "rationale_for", "confidence": "EXTRACTED", "source_file": "/home/Martin/Dominion/data_pipeline/sources/base.py", "source_location": "L29", "weight": 1.0}, {"source": "sources_base_rationale_33", "target": "sources_base_datasource_health", "relation": "rationale_for", "confidence": "EXTRACTED", "source_file": "/home/Martin/Dominion/data_pipeline/sources/base.py", "source_location": "L33", "weight": 1.0}, {"source": "sources_base_rationale_42", "target": "sources_base_datasource_mark_success", "relation": "rationale_for", "confidence": "EXTRACTED", "source_file": "/home/Martin/Dominion/data_pipeline/sources/base.py", "source_location": "L42", "weight": 1.0}], "raw_calls": [{"caller_nid": "sources_base_datasource_mark_success", "callee": "now", "is_member_call": true, "source_file": "/home/Martin/Dominion/data_pipeline/sources/base.py", "source_location": "L43"}]}